gfn_kernels.cp313-win_amd64.pyd
gfn/__init__.py
gfn/adjoint.py
gfn/embeddings.py
gfn/geometry.py
gfn/layers.py
gfn/losses.py
gfn/math_dataset.py
gfn/mixed_dataset.py
gfn/model.py
gfn/optim.py
gfn/readout.py
gfn/safety.py
gfn/scan.py
gfn/visualize.py
gfn/csrc/bindings.cpp
gfn/csrc/fused_ops.cu
gfn/cuda/__init__.py
gfn/cuda/ops.py
gfn/cuda/ops_scons.py
gfn/cuda/precompile_kernels.py
gfn/cuda/setup.py
gfn/cuda/test_kernel_load.py
gfn-2.6.1.dist-info/licenses/LICENSE
gfn-2.6.1.dist-info/licenses/NOTICE
gfn-2.6.1.dist-info/METADATA
gfn-2.6.1.dist-info/WHEEL
gfn-2.6.1.dist-info/top_level.txt
gfn-2.6.1.dist-info/RECORD
