Metadata-Version: 2.4
Name: gfn
Version: 2.6.1
Summary: Manifold: Geometric Intelligence via Symplectic Geodesic Flows | GFN: Geometric Flow Networks
Author-email: "Manifold Laboratory (Joaquín Stürtz)" <ManifoldLabs@proton.me>
License: Apache-2.0
Project-URL: Homepage, https://github.com/Manifold-Laboratory/manifold
Project-URL: Documentation, https://github.com/Manifold-Laboratory/manifold/tree/main/docs
Project-URL: Repository, https://github.com/Manifold-Laboratory/manifold.git
Project-URL: Issues, https://github.com/Manifold-Laboratory/manifold/issues
Keywords: artificial-intelligence,deep-learning,riemannian-geometry,symplectic-integration,sequence-modeling,geometric-deep-learning
Classifier: Development Status :: 5 - Production/Stable
Classifier: Intended Audience :: Science/Research
Classifier: Intended Audience :: Developers
Classifier: License :: OSI Approved :: Apache Software License
Classifier: Programming Language :: Python :: 3.10
Classifier: Programming Language :: Python :: 3.11
Classifier: Topic :: Scientific/Engineering :: Artificial Intelligence
Classifier: Topic :: Scientific/Engineering :: Mathematics
Classifier: Operating System :: OS Independent
Requires-Python: >=3.10
License-File: LICENSE
License-File: NOTICE
Requires-Dist: torch>=2.0.0
Requires-Dist: numpy>=1.24.0
Requires-Dist: pyyaml>=6.0
Requires-Dist: matplotlib>=3.7.0
Requires-Dist: pynvml>=11.5.0
Provides-Extra: dev
Requires-Dist: pytest>=7.4.0; extra == "dev"
Requires-Dist: pytest-cov>=4.1.0; extra == "dev"
Requires-Dist: black>=23.7.0; extra == "dev"
Requires-Dist: isort>=5.12.0; extra == "dev"
Requires-Dist: flake8>=6.1.0; extra == "dev"
Provides-Extra: cuda
Requires-Dist: ninja>=1.11.1; extra == "cuda"
Dynamic: license-file
